privyfilter/__init__.py
privyfilter/people.py
privyfilter/privyfilter.py
privyfilter/Configs/haarcascade_frontalface_default.xml
privyfilter/peoplemod/__init__.py
privyfilter/peoplemod/face_detection.py
privyfilter/peoplemod/face_swap.py
privyfilter-0.2.494.dist-info/LICENSE
privyfilter-0.2.494.dist-info/METADATA
privyfilter-0.2.494.dist-info/WHEEL
privyfilter-0.2.494.dist-info/top_level.txt
privyfilter-0.2.494.dist-info/RECORD
