Metadata-Version: 2.1
Name: privyfilter
Version: 0.2.494
Summary: Photo filter for decreasing bias in photo datasets by generating synthetic matching photos
Home-page: https://github.com/deamoner/privyfilter
Author: Matthew Davis
Author-email: mdavis@virtustructure.com
License: MIT
Keywords: photo sythetic bias privacy de-identification anonymization
Platform: UNKNOWN
Requires-Dist: numpy (>=1.18.4)
Requires-Dist: opencv-python (>=4.2.0.34)
Requires-Dist: Pillow (>=7.1.2)
Requires-Dist: thisapidoesnotexist (>=0.2)
Requires-Dist: gdown (>=3.10.1)
